{tadadada
    "data": [{
            "author": "",
            "title": ""
        }],
    "slide": [
    .................................;
        {
            "type": "slide",
            "hierarchy" : 2.3
            "pos":
                    {
                        "x": 100,
                        "y": 200,
                        "z": 0
                    },
            "scale": 2,
            "element": [
                {
                    "type": "text",
                    "pos": {
                        "x": 50,
                        "y": 50,
                        "z": 0
                    },
                    "rotate": {
                        "x": 0,
                        "y": 0,
                        "z": 0
                    },
                    "hierarchy": "h1",
                    "content": "Deuxieme Partie, Petit C",
                    "attributes": []
                }
            ]
        },
        
   .......


    ]


}

